AUTHORS.rst
LICENSE
MANIFEST.in
README.rst
setup.py
django_unfriendly.egg-info/PKG-INFO
django_unfriendly.egg-info/SOURCES.txt
django_unfriendly.egg-info/dependency_links.txt
django_unfriendly.egg-info/not-zip-safe
django_unfriendly.egg-info/requires.txt
django_unfriendly.egg-info/top_level.txt
tests/__init__.py
tests/settings.py
tests/tests.py
tests/urls.py
tests/views.py
unfriendly/__init__.py
unfriendly/models.py
unfriendly/settings.py
unfriendly/urls.py
unfriendly/utils.py
unfriendly/views.py
unfriendly/templatetags/__init__.py
unfriendly/templatetags/unfriendly_tags.py